pySpectrumFileFormat/__init__.py
pySpectrumFileFormat/microanalysis_file_format.py
pySpectrumFileFormat/tests.py
pySpectrumFileFormat/Bruker/ExportedCsvFile.py
pySpectrumFileFormat/Bruker/FileFormatRtx.py
pySpectrumFileFormat/Bruker/__init__.py
pySpectrumFileFormat/Bruker/MapRaw/MapRawFormat.py
pySpectrumFileFormat/Bruker/MapRaw/ParametersFile.py
pySpectrumFileFormat/Bruker/MapRaw/__init__.py
pySpectrumFileFormat/Bruker/MapRaw/test_MapRawFormat.py
pySpectrumFileFormat/Bruker/MapRaw/test_ParametersFile.py
pySpectrumFileFormat/Bruker/MapRaw/tests.py
pySpectrumFileFormat/EPMA/JEOL8900McGill.py
pySpectrumFileFormat/EPMA/__init__.py
pySpectrumFileFormat/EPMA/test_JEOL8900McGill.py
pySpectrumFileFormat/Edax/TemCsvFile.py
pySpectrumFileFormat/Edax/__init__.py
pySpectrumFileFormat/Edax/test_TemCsvFile.py
pySpectrumFileFormat/OxfordInstruments/__init__.py
pySpectrumFileFormat/OxfordInstruments/INCA/ReadAllSpectrumResults.py
pySpectrumFileFormat/OxfordInstruments/INCA/ReadSpectrumFullResults.py
pySpectrumFileFormat/OxfordInstruments/INCA/ReadSpectrumProcessingResults.py
pySpectrumFileFormat/OxfordInstruments/INCA/__init__.py
pySpectrumFileFormat/OxfordInstruments/INCA/test_ReadAllSpectrumResults.py
pySpectrumFileFormat/OxfordInstruments/INCA/test_ReadSpectrumFullResults.py
pySpectrumFileFormat/OxfordInstruments/INCA/test_ReadSpectrumProcessingResults.py
pySpectrumFileFormat/OxfordInstruments/MapRaw/MapRawFormat.py
pySpectrumFileFormat/OxfordInstruments/MapRaw/ParametersFile.py
pySpectrumFileFormat/OxfordInstruments/MapRaw/__init__.py
pySpectrumFileFormat/OxfordInstruments/MapRaw/test_MapRawFormat.py
pySpectrumFileFormat/OxfordInstruments/MapRaw/test_ParametersFile.py
pySpectrumFileFormat/OxfordInstruments/MapRaw/tests.py
pySpectrumFileFormat/VeriCold/TraceFile.py
pySpectrumFileFormat/VeriCold/__init__.py
pySpectrumFileFormat/VeriCold/genesisPolarisFile.py
pySpectrumFileFormat/VeriCold/test_TraceFile.py
pySpectrumFileFormat-0.1.dist-info/DESCRIPTION.rst
pySpectrumFileFormat-0.1.dist-info/METADATA
pySpectrumFileFormat-0.1.dist-info/RECORD
pySpectrumFileFormat-0.1.dist-info/WHEEL
pySpectrumFileFormat-0.1.dist-info/metadata.json
pySpectrumFileFormat-0.1.dist-info/top_level.txt
