Metadata-Version: 2.0
Name: pySpectrumFileFormat
Version: 0.1
Summary: Project to read and write various x-ray spectrum file format.
Home-page: UNKNOWN
Author: Hendrix Demers
Author-email: hendrix.demers@mail.mcgill.ca
License: Apache License, Version 2.0
Keywords: microanalysis_file_format
Platform: UNKNOWN
Classifier: Development Status :: 5 - Production/Stable
Classifier: Environment :: Console
Classifier: Intended Audience :: Developers
Classifier: Intended Audience :: Science/Research
Classifier: License :: OSI Approved :: Apache Software License
Classifier: Natural Language :: English
Classifier: Programming Language :: Python
Classifier: Operating System :: OS Independent
Classifier: Topic :: Scientific/Engineering
Requires-Dist: numpy
Requires-Dist: matplotlib
Requires-Dist: scipy
Requires-Dist: six
